COPYING
NEWS
setup.cfg
setup.py
LinkExchange.MoinMoin.egg-info/PKG-INFO
LinkExchange.MoinMoin.egg-info/SOURCES.txt
LinkExchange.MoinMoin.egg-info/dependency_links.txt
LinkExchange.MoinMoin.egg-info/namespace_packages.txt
LinkExchange.MoinMoin.egg-info/requires.txt
LinkExchange.MoinMoin.egg-info/top_level.txt
linkexchange/__init__.py
linkexchange/MoinMoin/__init__.py
linkexchange/MoinMoin/support.py
linkexchange/MoinMoin/action/LinkExchangeHandler.py
linkexchange/MoinMoin/action/__init__.py
linkexchange/MoinMoin/macro/LinkExchangeBlock.py
linkexchange/MoinMoin/macro/__init__.py
linkexchange/MoinMoin/parser/__init__.py
linkexchange/MoinMoin/parser/linkexchange_wiki.py
tests/__init__.py
tests/test_moin.py